Metadata-Version: 2.1
Name: real-easypy
Version: 0.5.0
Summary: easypy is a collection of python modules that makes developers happy
Home-page: https://github.com/real-easypy/easypy
Author: Ofer Koren
Author-email: koreno@gmail.com
License: BSD
Classifier: Programming Language :: Python :: 3
Classifier: License :: OSI Approved :: BSD License
Classifier: Operating System :: OS Independent
License-File: LICENSE
